rospy_yaml_include/__init__.py
rospy_yaml_include/yaml_include.py
rospy_yaml_include-3.0.2.dist-info/METADATA
rospy_yaml_include-3.0.2.dist-info/WHEEL
rospy_yaml_include-3.0.2.dist-info/top_level.txt
rospy_yaml_include-3.0.2.dist-info/RECORD
